{
  "generator-jhipster": {
    "applicationType": "monolith",
    "gitHubOrganization": "janakalakshmi",
    "baseName": "jhipsterSampleApplication",
    "packageName": "io.github.jhipster.application",
    "serverPort": 8080,
    "serviceDiscoveryType": false,
    "authenticationType": "session",
    "uaaBaseName": "../uaa",
    "hibernateCache": "no",
    "clusteredHttpSession": false,
    "websocket": false,
    "databaseType": "sql",
    "devDatabaseType": "h2Disk",
    "prodDatabaseType": "mysql",
    "searchEngine": false,
    "enableSwaggerCodegen": false,
    "messageBroker": "kafka",
    "buildTool": "gradle",
    "enableSocialSignIn": false,
    "useSass": false,
    "clientPackageManager": "yarn",
    "testFrameworks": [],
    "enableTranslation": false,
    "nativeLanguage": "en",
    "languages": [
      "en"
    ],
    "clientFramework": "angular1",
    "jhipsterVersion": "4.8.2",
    "packageFolder": "io/github/jhipster/application",
    "rememberMeKey": "2bfe594fa01a45de9371ce46f62c888d9ac9962f",
    "jhiPrefix": "jhi"
  }
}